cpgetools/graphs.py
cpgetools/heaps.py
cpgetools/trees.py
cpgetools-0.0.3.dist-info/LICENSE
cpgetools-0.0.3.dist-info/METADATA
cpgetools-0.0.3.dist-info/WHEEL
cpgetools-0.0.3.dist-info/top_level.txt
cpgetools-0.0.3.dist-info/RECORD
